AUTHORS
bin/finder.py
git_vuln_finder/__init__.py
git_vuln_finder/pattern.py
git_vuln_finder/patterns/en/medium/c
git_vuln_finder/patterns/en/medium/c.prefix
git_vuln_finder/patterns/en/medium/c.suffix
git_vuln_finder/patterns/en/medium/crypto
git_vuln_finder/patterns/en/medium/crypto.prefix
git_vuln_finder/patterns/en/medium/crypto.suffix
git_vuln_finder/patterns/en/medium/vuln
git_vuln_finder/patterns/en/medium/vuln.prefix
git_vuln_finder/patterns/en/medium/vuln.suffix
git_vuln_finder/run.py
git_vuln_finder/vulnerability.py
git_vuln_finder-1.4.dist-info/entry_points.txt
git_vuln_finder-1.4.dist-info/WHEEL
git_vuln_finder-1.4.dist-info/METADATA
git_vuln_finder-1.4.dist-info/RECORD
