Metadata-Version: 2.1
Name: git-vuln-finder
Version: 1.4
Summary: Finding potential software vulnerabilities from git commit messages.
Home-page: https://github.com/cve-search/git-vuln-finder
License: AGPL-3.0-or-later
Keywords: git,cve,scanner,cve-search,cve-scanning,software-vulnerability,software-vulnerabilities
Author: Alexandre Dulaunoy
Author-email: a@foo.be
Requires-Python: >=3.6,<4.0
Classifier: Environment :: Console
Classifier: Intended Audience :: Developers
Classifier: Intended Audience :: Information Technology
Classifier: Intended Audience :: Science/Research
Classifier: License :: OSI Approved :: GNU Affero General Public License v3 or later (AGPLv3+)
Classifier: Operating System :: OS Independent
Classifier: Programming Language :: Python :: 3
Classifier: Programming Language :: Python :: 3.6
Classifier: Programming Language :: Python :: 3.7
Classifier: Programming Language :: Python :: 3.8
Classifier: Programming Language :: Python :: 3.9
Classifier: Programming Language :: Python :: 3.10
Classifier: Programming Language :: Python :: 3.10
Classifier: Programming Language :: Python :: 3.6
Classifier: Programming Language :: Python :: 3.7
Classifier: Programming Language :: Python :: 3.8
Classifier: Topic :: Security
Requires-Dist: gitpython (>=3.0.5,<4.0.0)
Requires-Dist: langdetect (>=1.0.7,<2.0.0)
Requires-Dist: pymisp (>=2.4.128,<3.0.0)
Project-URL: Repository, https://github.com/cve-search/git-vuln-finder
